<?xml version="1.0" encoding="UTF-8" standalone="yes"?>
<Result>
	<Pages>
		<Page Id="0060">
			<Timings>
				<Time>0</Time>
				<Latency>0</Latency>
			</Timings>
			<Barcodes>
				<Barcode Type="EAN13">
					<Polygon>
						<Points>
							<Point X="828" Y="1977"/>
							<Point X="2372" Y="2040"/>
							<Point X="2322" Y="3137"/>
							<Point X="779" Y="3034"/>
						</Points>
					</Polygon>
					<Value>5907653103155</Value>
				</Barcode>
			</Barcodes>
		</Page>
	</Pages>
</Result>
