<?xml version="1.0" encoding="UTF-8" standalone="yes"?>
<Result>
	<Pages>
		<Page Id="0037">
			<Timings>
				<Time>0</Time>
				<Latency>0</Latency>
			</Timings>
			<Barcodes>
				<Barcode Type="PDF417">
					<Polygon>
						<Points>
							<Point X="508" Y="218"/>
							<Point X="566" Y="216"/>
							<Point X="576" Y="312"/>
							<Point X="516" Y="313"/>
						</Points>
					</Polygon>
					<Value>^</Value>
				</Barcode>
			</Barcodes>
		</Page>
	</Pages>
</Result>
